LICENSE
MANIFEST.in
README.rst
setup.cfg
setup.py
test_settings.py
django_helpcenter.egg-info/PKG-INFO
django_helpcenter.egg-info/SOURCES.txt
django_helpcenter.egg-info/dependency_links.txt
django_helpcenter.egg-info/not-zip-safe
django_helpcenter.egg-info/requires.txt
django_helpcenter.egg-info/top_level.txt
docs/Makefile
docs/conf.py
docs/configuration.rst
docs/index.rst
docs/installation.rst
docs/release notes.rst
helpcenter/__init__.py
helpcenter/admin.py
helpcenter/mixins.py
helpcenter/models.py
helpcenter/testing_utils.py
helpcenter/urls.py
helpcenter/utils.py
helpcenter/views.py
helpcenter/api/__init__.py
helpcenter/api/serializers.py
helpcenter/api/testing_utils.py
helpcenter/api/urls.py
helpcenter/api/views.py
helpcenter/api/tests/__init__.py
helpcenter/api/tests/test_serializers.py
helpcenter/api/tests/test_views.py
helpcenter/migrations/0001_initial.py
helpcenter/migrations/0002_category.py
helpcenter/migrations/0003_article_category.py
helpcenter/migrations/0004_auto_20160607_1234.py
helpcenter/migrations/0005_article_time_edited.py
helpcenter/migrations/0006_auto_20160715_1917.py
helpcenter/migrations/0007_auto_20160715_1922.py
helpcenter/migrations/0008_article_draft.py
helpcenter/migrations/0009_category_slug_squashed_0011_auto_20160928_0840.py
helpcenter/migrations/0010_auto_20160929_2247.py
helpcenter/migrations/__init__.py
helpcenter/tests/__init__.py
helpcenter/tests/dummy_classes.py
helpcenter/tests/test_models.py
helpcenter/tests/test_utils.py
helpcenter/tests/test_views.py