Metadata-Version: 1.1
Name: django-helpcenter
Version: 1.0.0
Summary: Django app for creating a help section
Home-page: http://github.com/smalls12/django_helpcenter
Author: Chathan Driehuys
Author-email: cdriehuys@gmail.com
License: MIT
Platform: UNKNOWN
Classifier: Development Status :: 3 - Alpha
Classifier: Environment :: Web Environment
Classifier: Framework :: Django :: 1.8
Classifier: Framework :: Django :: 1.9
Classifier: Intended Audience :: Developers
Classifier: License :: OSI Approved :: MIT License
Classifier: Programming Language :: Python :: 2.7
Classifier: Programming Language :: Python :: 3.3
Classifier: Programming Language :: Python :: 3.4
Classifier: Programming Language :: Python :: 3.5
